yaml_translator/__init__.py
yaml_translator/translator.py
yaml_translator/package/__init__.py
yaml_translator/package/package_utils.py
yaml_translator-1.0.1.dist-info/LICENSE
yaml_translator-1.0.1.dist-info/METADATA
yaml_translator-1.0.1.dist-info/WHEEL
yaml_translator-1.0.1.dist-info/top_level.txt
yaml_translator-1.0.1.dist-info/RECORD
